minireason/__init__.py
minireason/evaluation.py
minireason/solvers.py
minireason/sweep.py
minireason/sweep_plotting.py
minireason/task_list.py
minireason/tasks.py
minireason-0.1.0.dist-info/WHEEL
minireason-0.1.0.dist-info/METADATA
minireason-0.1.0.dist-info/RECORD
