Metadata-Version: 2.3
Name: minireason
Version: 0.1.0
Summary: Symbolic reasoning playground and benchmark
Author: Patrick Spencer
Author-email: Patrick Spencer <patrickwspencer@gmail.com>
License: MIT
Classifier: Development Status :: 3 - Alpha
Classifier: Programming Language :: Python :: 3.12
Requires-Dist: matplotlib>=3.10.6
Requires-Dist: tqdm>=4.67.1
Requires-Python: >=3.12
